yfpy_nhl_sqlite/__init__.py
yfpy_nhl_sqlite/main.py
yfpy_nhl_sqlite/queries.py
yfpy_nhl_sqlite/schema.sql
yfpy_nhl_sqlite-1.0.0.dist-info/METADATA
yfpy_nhl_sqlite-1.0.0.dist-info/WHEEL
yfpy_nhl_sqlite-1.0.0.dist-info/entry_points.txt
yfpy_nhl_sqlite-1.0.0.dist-info/licenses/LICENSE
yfpy_nhl_sqlite-1.0.0.dist-info/RECORD
