Metadata-Version: 2.4
Name: yfpy-nhl-sqlite
Version: 1.0.0
Summary: Script for creating a sqlite3 db from Yahoo NHL fantasy league data using yfpy.
Project-URL: Homepage, https://github.com/j-krl/yfpy-nhl-sqlite/
Project-URL: Repository, https://github.com/j-krl/yfpy-nhl-sqlite/
Project-URL: Issues, https://github.com/j-krl/yfpy-nhl-sqlite/issues
Author-email: Jesse Kearl <jessekearl@gmail.com>
License-Expression: GPL-3.0-or-later
License-File: LICENSE
Keywords: fantasy,hockey,nhl,sports,sqlite,yahoo,yfpy
Classifier: Development Status :: 5 - Production/Stable
Classifier: Programming Language :: Python :: 3
Classifier: Programming Language :: Python :: 3.10
Classifier: Programming Language :: Python :: 3.11
Classifier: Programming Language :: Python :: 3.12
Classifier: Programming Language :: Python :: 3.13
Requires-Python: >=3.10
Requires-Dist: requests>=2.32.3
Requires-Dist: yfpy>=16.0.3
Provides-Extra: dev
Requires-Dist: ipython; extra == 'dev'
Requires-Dist: ruff; extra == 'dev'
